ak_cache/__init__.py
ak_cache/main.py
ak_cache-0.0.5.dist-info/LICENSE
ak_cache-0.0.5.dist-info/WHEEL
ak_cache-0.0.5.dist-info/METADATA
ak_cache-0.0.5.dist-info/RECORD
