Metadata-Version: 2.1
Name: ak_cache
Version: 0.0.5
Summary: General Cache File to cache anything you like
Author-email: Arun Kishore <pypi@rpakishore.co.in>
Classifier: License :: OSI Approved :: MIT License
Requires-Dist: ak_file
Requires-Dist: pytest
Requires-Dist: cryptography
Project-URL: Home, https://github.com/rpakishore/ak_cache
